[
  {
    "text": "Rohini mein water supply improve hui hai, good initiative",
    "source": "twitter",
    "location": "Delhi",
    "ward": "Rohini"
  },
  {
    "text": "Rohini mein water supply improve hui hai, good initiative issue abhi tak resolve nahi hua",
    "source": "twitter",
    "location": "Delhi",
    "ward": "Rohini"
  },
  {
    "text": "Rohini mein water supply improve hui hai, good initiative situation abhi bhi concerning hai",
    "source": "twitter",
    "location": "Delhi",
    "ward": "Rohini"
  },
  {
    "text": "Rohini mein water supply improve hui hai, good initiative authorities ko action lena chahiye",
    "source": "twitter",
    "location": "Delhi",
    "ward": "Rohini"
  },
  {
    "text": "Rohini mein water supply improve hui hai, good initiative logon ko dikkat ho rahi hai",
    "source": "twitter",
    "location": "Delhi",
    "ward": "Rohini"
  },
  {
    "text": "Dwarka mein bijli cuts bahut ho rahe hain",
    "source": "twitter",
    "location": "Delhi",
    "ward": "Dwarka"
  },
  {
    "text": "Dwarka mein bijli cuts bahut ho rahe hain authorities ko action lena chahiye",
    "source": "twitter",
    "location": "Delhi",
    "ward": "Dwarka"
  },
  {
    "text": "Dwarka mein bijli cuts bahut ho rahe hain logon ko dikkat ho rahi hai",
    "source": "twitter",
    "location": "Delhi",
    "ward": "Dwarka"
  },
  {
    "text": "Dwarka mein bijli cuts bahut ho rahe hain situation abhi bhi concerning hai",
    "source": "twitter",
    "location": "Delhi",
    "ward": "Dwarka"
  },
  {
    "text": "Dwarka mein bijli cuts bahut ho rahe hain issue abhi tak resolve nahi hua",
    "source": "twitter",
    "location": "Delhi",
    "ward": "Dwarka"
  },
  {
    "text": "Janakpuri traffic aaj kaafi smooth tha",
    "source": "news",
    "location": "Delhi",
    "ward": "Janakpuri"
  },
  {
    "text": "Janakpuri traffic aaj kaafi smooth tha issue abhi tak resolve nahi hua",
    "source": "news",
    "location": "Delhi",
    "ward": "Janakpuri"
  },
  {
    "text": "Janakpuri traffic aaj kaafi smooth tha issue abhi tak resolve nahi hua",
    "source": "news",
    "location": "Delhi",
    "ward": "Janakpuri"
  },
  {
    "text": "Janakpuri traffic aaj kaafi smooth tha logon ko dikkat ho rahi hai",
    "source": "news",
    "location": "Delhi",
    "ward": "Janakpuri"
  },
  {
    "text": "Janakpuri traffic aaj kaafi smooth tha authorities ko action lena chahiye",
    "source": "news",
    "location": "Delhi",
    "ward": "Janakpuri"
  },
  {
    "text": "Saket mein pollution level badh raha hai",
    "source": "twitter",
    "location": "Delhi",
    "ward": "Saket"
  },
  {
    "text": "Saket mein pollution level badh raha hai situation abhi bhi concerning hai",
    "source": "twitter",
    "location": "Delhi",
    "ward": "Saket"
  },
  {
    "text": "Saket mein pollution level badh raha hai kaafi improvement ki zarurat hai",
    "source": "twitter",
    "location": "Delhi",
    "ward": "Saket"
  },
  {
    "text": "Saket mein pollution level badh raha hai situation abhi bhi concerning hai",
    "source": "twitter",
    "location": "Delhi",
    "ward": "Saket"
  },
  {
    "text": "Saket mein pollution level badh raha hai authorities ko action lena chahiye",
    "source": "twitter",
    "location": "Delhi",
    "ward": "Saket"
  },
  {
    "text": "Pitampura mein water supply thodi irregular hai",
    "source": "twitter",
    "location": "Delhi",
    "ward": "Pitampura"
  },
  {
    "text": "Pitampura mein water supply thodi irregular hai logon ko dikkat ho rahi hai",
    "source": "twitter",
    "location": "Delhi",
    "ward": "Pitampura"
  },
  {
    "text": "Pitampura mein water supply thodi irregular hai logon ko dikkat ho rahi hai",
    "source": "twitter",
    "location": "Delhi",
    "ward": "Pitampura"
  },
  {
    "text": "Pitampura mein water supply thodi irregular hai issue abhi tak resolve nahi hua",
    "source": "twitter",
    "location": "Delhi",
    "ward": "Pitampura"
  },
  {
    "text": "Pitampura mein water supply thodi irregular hai situation abhi bhi concerning hai",
    "source": "twitter",
    "location": "Delhi",
    "ward": "Pitampura"
  },
  {
    "text": "Lajpat Nagar roads clean aur well maintained hain",
    "source": "news",
    "location": "Delhi",
    "ward": "Lajpat Nagar"
  },
  {
    "text": "Lajpat Nagar roads clean aur well maintained hain kaafi improvement ki zarurat hai",
    "source": "news",
    "location": "Delhi",
    "ward": "Lajpat Nagar"
  },
  {
    "text": "Lajpat Nagar roads clean aur well maintained hain issue abhi tak resolve nahi hua",
    "source": "news",
    "location": "Delhi",
    "ward": "Lajpat Nagar"
  },
  {
    "text": "Lajpat Nagar roads clean aur well maintained hain authorities ko action lena chahiye",
    "source": "news",
    "location": "Delhi",
    "ward": "Lajpat Nagar"
  },
  {
    "text": "Lajpat Nagar roads clean aur well maintained hain situation abhi bhi concerning hai",
    "source": "news",
    "location": "Delhi",
    "ward": "Lajpat Nagar"
  },
  {
    "text": "Karol Bagh traffic peak hours mein bahut heavy hota hai",
    "source": "twitter",
    "location": "Delhi",
    "ward": "Karol Bagh"
  },
  {
    "text": "Karol Bagh traffic peak hours mein bahut heavy hota hai kaafi improvement ki zarurat hai",
    "source": "twitter",
    "location": "Delhi",
    "ward": "Karol Bagh"
  },
  {
    "text": "Karol Bagh traffic peak hours mein bahut heavy hota hai kaafi improvement ki zarurat hai",
    "source": "twitter",
    "location": "Delhi",
    "ward": "Karol Bagh"
  },
  {
    "text": "Karol Bagh traffic peak hours mein bahut heavy hota hai kaafi improvement ki zarurat hai",
    "source": "twitter",
    "location": "Delhi",
    "ward": "Karol Bagh"
  },
  {
    "text": "Karol Bagh traffic peak hours mein bahut heavy hota hai logon ko dikkat ho rahi hai",
    "source": "twitter",
    "location": "Delhi",
    "ward": "Karol Bagh"
  },
  {
    "text": "Vasant Kunj mein electricity stable hai",
    "source": "news",
    "location": "Delhi",
    "ward": "Vasant Kunj"
  },
  {
    "text": "Vasant Kunj mein electricity stable hai logon ko dikkat ho rahi hai",
    "source": "news",
    "location": "Delhi",
    "ward": "Vasant Kunj"
  },
  {
    "text": "Vasant Kunj mein electricity stable hai kaafi improvement ki zarurat hai",
    "source": "news",
    "location": "Delhi",
    "ward": "Vasant Kunj"
  },
  {
    "text": "Vasant Kunj mein electricity stable hai situation abhi bhi concerning hai",
    "source": "news",
    "location": "Delhi",
    "ward": "Vasant Kunj"
  },
  {
    "text": "Vasant Kunj mein electricity stable hai kaafi improvement ki zarurat hai",
    "source": "news",
    "location": "Delhi",
    "ward": "Vasant Kunj"
  },
  {
    "text": "Shahdara mein paani ki problem abhi bhi hai",
    "source": "twitter",
    "location": "Delhi",
    "ward": "Shahdara"
  },
  {
    "text": "Shahdara mein paani ki problem abhi bhi hai logon ko dikkat ho rahi hai",
    "source": "twitter",
    "location": "Delhi",
    "ward": "Shahdara"
  },
  {
    "text": "Shahdara mein paani ki problem abhi bhi hai situation abhi bhi concerning hai",
    "source": "twitter",
    "location": "Delhi",
    "ward": "Shahdara"
  },
  {
    "text": "Shahdara mein paani ki problem abhi bhi hai situation abhi bhi concerning hai",
    "source": "twitter",
    "location": "Delhi",
    "ward": "Shahdara"
  },
  {
    "text": "Shahdara mein paani ki problem abhi bhi hai situation abhi bhi concerning hai",
    "source": "twitter",
    "location": "Delhi",
    "ward": "Shahdara"
  },
  {
    "text": "Mayur Vihar pollution level moderate hai",
    "source": "news",
    "location": "Delhi",
    "ward": "Mayur Vihar"
  },
  {
    "text": "Mayur Vihar pollution level moderate hai kaafi improvement ki zarurat hai",
    "source": "news",
    "location": "Delhi",
    "ward": "Mayur Vihar"
  },
  {
    "text": "Mayur Vihar pollution level moderate hai authorities ko action lena chahiye",
    "source": "news",
    "location": "Delhi",
    "ward": "Mayur Vihar"
  },
  {
    "text": "Mayur Vihar pollution level moderate hai situation abhi bhi concerning hai",
    "source": "news",
    "location": "Delhi",
    "ward": "Mayur Vihar"
  },
  {
    "text": "Mayur Vihar pollution level moderate hai authorities ko action lena chahiye",
    "source": "news",
    "location": "Delhi",
    "ward": "Mayur Vihar"
  },
  {
    "text": "Vikaspuri traffic manageable hai aaj",
    "source": "twitter",
    "location": "Delhi",
    "ward": "Vikaspuri"
  },
  {
    "text": "Vikaspuri traffic manageable hai aaj authorities ko action lena chahiye",
    "source": "twitter",
    "location": "Delhi",
    "ward": "Vikaspuri"
  },
  {
    "text": "Vikaspuri traffic manageable hai aaj issue abhi tak resolve nahi hua",
    "source": "twitter",
    "location": "Delhi",
    "ward": "Vikaspuri"
  },
  {
    "text": "Vikaspuri traffic manageable hai aaj issue abhi tak resolve nahi hua",
    "source": "twitter",
    "location": "Delhi",
    "ward": "Vikaspuri"
  },
  {
    "text": "Vikaspuri traffic manageable hai aaj logon ko dikkat ho rahi hai",
    "source": "twitter",
    "location": "Delhi",
    "ward": "Vikaspuri"
  },
  {
    "text": "Rajouri Garden roads clean hain aur maintenance acha hai",
    "source": "news",
    "location": "Delhi",
    "ward": "Rajouri Garden"
  },
  {
    "text": "Rajouri Garden roads clean hain aur maintenance acha hai authorities ko action lena chahiye",
    "source": "news",
    "location": "Delhi",
    "ward": "Rajouri Garden"
  },
  {
    "text": "Rajouri Garden roads clean hain aur maintenance acha hai authorities ko action lena chahiye",
    "source": "news",
    "location": "Delhi",
    "ward": "Rajouri Garden"
  },
  {
    "text": "Rajouri Garden roads clean hain aur maintenance acha hai kaafi improvement ki zarurat hai",
    "source": "news",
    "location": "Delhi",
    "ward": "Rajouri Garden"
  },
  {
    "text": "Rajouri Garden roads clean hain aur maintenance acha hai kaafi improvement ki zarurat hai",
    "source": "news",
    "location": "Delhi",
    "ward": "Rajouri Garden"
  },
  {
    "text": "Nehru Place mein traffic jam roz ka issue hai",
    "source": "twitter",
    "location": "Delhi",
    "ward": "Nehru Place"
  },
  {
    "text": "Nehru Place mein traffic jam roz ka issue hai situation abhi bhi concerning hai",
    "source": "twitter",
    "location": "Delhi",
    "ward": "Nehru Place"
  },
  {
    "text": "Nehru Place mein traffic jam roz ka issue hai situation abhi bhi concerning hai",
    "source": "twitter",
    "location": "Delhi",
    "ward": "Nehru Place"
  },
  {
    "text": "Nehru Place mein traffic jam roz ka issue hai situation abhi bhi concerning hai",
    "source": "twitter",
    "location": "Delhi",
    "ward": "Nehru Place"
  },
  {
    "text": "Nehru Place mein traffic jam roz ka issue hai kaafi improvement ki zarurat hai",
    "source": "twitter",
    "location": "Delhi",
    "ward": "Nehru Place"
  },
  {
    "text": "Patel Nagar mein water supply consistent hai",
    "source": "news",
    "location": "Delhi",
    "ward": "Patel Nagar"
  },
  {
    "text": "Patel Nagar mein water supply consistent hai issue abhi tak resolve nahi hua",
    "source": "news",
    "location": "Delhi",
    "ward": "Patel Nagar"
  },
  {
    "text": "Patel Nagar mein water supply consistent hai logon ko dikkat ho rahi hai",
    "source": "news",
    "location": "Delhi",
    "ward": "Patel Nagar"
  },
  {
    "text": "Patel Nagar mein water supply consistent hai logon ko dikkat ho rahi hai",
    "source": "news",
    "location": "Delhi",
    "ward": "Patel Nagar"
  },
  {
    "text": "Patel Nagar mein water supply consistent hai issue abhi tak resolve nahi hua",
    "source": "news",
    "location": "Delhi",
    "ward": "Patel Nagar"
  },
  {
    "text": "Mustafabad pollution level high hai",
    "source": "twitter",
    "location": "Delhi",
    "ward": "Mustafabad"
  },
  {
    "text": "Mustafabad pollution level high hai logon ko dikkat ho rahi hai",
    "source": "twitter",
    "location": "Delhi",
    "ward": "Mustafabad"
  },
  {
    "text": "Mustafabad pollution level high hai authorities ko action lena chahiye",
    "source": "twitter",
    "location": "Delhi",
    "ward": "Mustafabad"
  },
  {
    "text": "Mustafabad pollution level high hai situation abhi bhi concerning hai",
    "source": "twitter",
    "location": "Delhi",
    "ward": "Mustafabad"
  },
  {
    "text": "Mustafabad pollution level high hai issue abhi tak resolve nahi hua",
    "source": "twitter",
    "location": "Delhi",
    "ward": "Mustafabad"
  },
  {
    "text": "Tilak Nagar mein bijli stable hai",
    "source": "news",
    "location": "Delhi",
    "ward": "Tilak Nagar"
  },
  {
    "text": "Tilak Nagar mein bijli stable hai issue abhi tak resolve nahi hua",
    "source": "news",
    "location": "Delhi",
    "ward": "Tilak Nagar"
  },
  {
    "text": "Tilak Nagar mein bijli stable hai authorities ko action lena chahiye",
    "source": "news",
    "location": "Delhi",
    "ward": "Tilak Nagar"
  },
  {
    "text": "Tilak Nagar mein bijli stable hai authorities ko action lena chahiye",
    "source": "news",
    "location": "Delhi",
    "ward": "Tilak Nagar"
  },
  {
    "text": "Tilak Nagar mein bijli stable hai authorities ko action lena chahiye",
    "source": "news",
    "location": "Delhi",
    "ward": "Tilak Nagar"
  },
  {
    "text": "Uttam Nagar traffic peak hours mein slow hota hai",
    "source": "twitter",
    "location": "Delhi",
    "ward": "Uttam Nagar"
  },
  {
    "text": "Uttam Nagar traffic peak hours mein slow hota hai logon ko dikkat ho rahi hai",
    "source": "twitter",
    "location": "Delhi",
    "ward": "Uttam Nagar"
  },
  {
    "text": "Uttam Nagar traffic peak hours mein slow hota hai logon ko dikkat ho rahi hai",
    "source": "twitter",
    "location": "Delhi",
    "ward": "Uttam Nagar"
  },
  {
    "text": "Uttam Nagar traffic peak hours mein slow hota hai situation abhi bhi concerning hai",
    "source": "twitter",
    "location": "Delhi",
    "ward": "Uttam Nagar"
  },
  {
    "text": "Uttam Nagar traffic peak hours mein slow hota hai issue abhi tak resolve nahi hua",
    "source": "twitter",
    "location": "Delhi",
    "ward": "Uttam Nagar"
  },
  {
    "text": "Mehrauli roads kaafi clean hain",
    "source": "news",
    "location": "Delhi",
    "ward": "Mehrauli"
  },
  {
    "text": "Mehrauli roads kaafi clean hain kaafi improvement ki zarurat hai",
    "source": "news",
    "location": "Delhi",
    "ward": "Mehrauli"
  },
  {
    "text": "Mehrauli roads kaafi clean hain logon ko dikkat ho rahi hai",
    "source": "news",
    "location": "Delhi",
    "ward": "Mehrauli"
  },
  {
    "text": "Mehrauli roads kaafi clean hain logon ko dikkat ho rahi hai",
    "source": "news",
    "location": "Delhi",
    "ward": "Mehrauli"
  },
  {
    "text": "Mehrauli roads kaafi clean hain kaafi improvement ki zarurat hai",
    "source": "news",
    "location": "Delhi",
    "ward": "Mehrauli"
  },
  {
    "text": "Geeta Colony water supply irregular hai",
    "source": "twitter",
    "location": "Delhi",
    "ward": "Geeta Colony"
  },
  {
    "text": "Geeta Colony water supply irregular hai logon ko dikkat ho rahi hai",
    "source": "twitter",
    "location": "Delhi",
    "ward": "Geeta Colony"
  },
  {
    "text": "Geeta Colony water supply irregular hai situation abhi bhi concerning hai",
    "source": "twitter",
    "location": "Delhi",
    "ward": "Geeta Colony"
  },
  {
    "text": "Geeta Colony water supply irregular hai kaafi improvement ki zarurat hai",
    "source": "twitter",
    "location": "Delhi",
    "ward": "Geeta Colony"
  },
  {
    "text": "Geeta Colony water supply irregular hai logon ko dikkat ho rahi hai",
    "source": "twitter",
    "location": "Delhi",
    "ward": "Geeta Colony"
  },
  {
    "text": "Connaught Place traffic smooth tha aaj",
    "source": "news",
    "location": "Delhi",
    "ward": "Connaught Place"
  },
  {
    "text": "Connaught Place traffic smooth tha aaj issue abhi tak resolve nahi hua",
    "source": "news",
    "location": "Delhi",
    "ward": "Connaught Place"
  },
  {
    "text": "Connaught Place traffic smooth tha aaj kaafi improvement ki zarurat hai",
    "source": "news",
    "location": "Delhi",
    "ward": "Connaught Place"
  },
  {
    "text": "Connaught Place traffic smooth tha aaj kaafi improvement ki zarurat hai",
    "source": "news",
    "location": "Delhi",
    "ward": "Connaught Place"
  },
  {
    "text": "Connaught Place traffic smooth tha aaj kaafi improvement ki zarurat hai",
    "source": "news",
    "location": "Delhi",
    "ward": "Connaught Place"
  },
  {
    "text": "Burari pollution level dangerous ho gaya hai",
    "source": "twitter",
    "location": "Delhi",
    "ward": "Burari"
  },
  {
    "text": "Burari pollution level dangerous ho gaya hai authorities ko action lena chahiye",
    "source": "twitter",
    "location": "Delhi",
    "ward": "Burari"
  },
  {
    "text": "Burari pollution level dangerous ho gaya hai situation abhi bhi concerning hai",
    "source": "twitter",
    "location": "Delhi",
    "ward": "Burari"
  },
  {
    "text": "Burari pollution level dangerous ho gaya hai situation abhi bhi concerning hai",
    "source": "twitter",
    "location": "Delhi",
    "ward": "Burari"
  },
  {
    "text": "Burari pollution level dangerous ho gaya hai issue abhi tak resolve nahi hua",
    "source": "twitter",
    "location": "Delhi",
    "ward": "Burari"
  },
  {
    "text": "Narela mein water supply improve hui hai",
    "source": "news",
    "location": "Delhi",
    "ward": "Narela"
  },
  {
    "text": "Narela mein water supply improve hui hai authorities ko action lena chahiye",
    "source": "news",
    "location": "Delhi",
    "ward": "Narela"
  },
  {
    "text": "Narela mein water supply improve hui hai authorities ko action lena chahiye",
    "source": "news",
    "location": "Delhi",
    "ward": "Narela"
  },
  {
    "text": "Narela mein water supply improve hui hai kaafi improvement ki zarurat hai",
    "source": "news",
    "location": "Delhi",
    "ward": "Narela"
  },
  {
    "text": "Narela mein water supply improve hui hai kaafi improvement ki zarurat hai",
    "source": "news",
    "location": "Delhi",
    "ward": "Narela"
  },
  {
    "text": "Laxmi Nagar mein traffic bahut zyada hai",
    "source": "twitter",
    "location": "Delhi",
    "ward": "Laxmi Nagar"
  },
  {
    "text": "Laxmi Nagar mein traffic bahut zyada hai situation abhi bhi concerning hai",
    "source": "twitter",
    "location": "Delhi",
    "ward": "Laxmi Nagar"
  },
  {
    "text": "Laxmi Nagar mein traffic bahut zyada hai authorities ko action lena chahiye",
    "source": "twitter",
    "location": "Delhi",
    "ward": "Laxmi Nagar"
  },
  {
    "text": "Laxmi Nagar mein traffic bahut zyada hai logon ko dikkat ho rahi hai",
    "source": "twitter",
    "location": "Delhi",
    "ward": "Laxmi Nagar"
  },
  {
    "text": "Laxmi Nagar mein traffic bahut zyada hai kaafi improvement ki zarurat hai",
    "source": "twitter",
    "location": "Delhi",
    "ward": "Laxmi Nagar"
  },
  {
    "text": "Malviya Nagar mein roads theek hain aur traffic manageable hai",
    "source": "news",
    "location": "Delhi",
    "ward": "Malviya Nagar"
  },
  {
    "text": "Malviya Nagar mein roads theek hain aur traffic manageable hai kaafi improvement ki zarurat hai",
    "source": "news",
    "location": "Delhi",
    "ward": "Malviya Nagar"
  },
  {
    "text": "Malviya Nagar mein roads theek hain aur traffic manageable hai kaafi improvement ki zarurat hai",
    "source": "news",
    "location": "Delhi",
    "ward": "Malviya Nagar"
  },
  {
    "text": "Malviya Nagar mein roads theek hain aur traffic manageable hai issue abhi tak resolve nahi hua",
    "source": "news",
    "location": "Delhi",
    "ward": "Malviya Nagar"
  },
  {
    "text": "Malviya Nagar mein roads theek hain aur traffic manageable hai situation abhi bhi concerning hai",
    "source": "news",
    "location": "Delhi",
    "ward": "Malviya Nagar"
  },
  {
    "text": "Trilokpuri mein water logging issue hai",
    "source": "twitter",
    "location": "Delhi",
    "ward": "Trilokpuri"
  },
  {
    "text": "Trilokpuri mein water logging issue hai issue abhi tak resolve nahi hua",
    "source": "twitter",
    "location": "Delhi",
    "ward": "Trilokpuri"
  },
  {
    "text": "Trilokpuri mein water logging issue hai issue abhi tak resolve nahi hua",
    "source": "twitter",
    "location": "Delhi",
    "ward": "Trilokpuri"
  },
  {
    "text": "Trilokpuri mein water logging issue hai issue abhi tak resolve nahi hua",
    "source": "twitter",
    "location": "Delhi",
    "ward": "Trilokpuri"
  },
  {
    "text": "Trilokpuri mein water logging issue hai issue abhi tak resolve nahi hua",
    "source": "twitter",
    "location": "Delhi",
    "ward": "Trilokpuri"
  },
  {
    "text": "Ashok Vihar traffic thoda better hua hai",
    "source": "news",
    "location": "Delhi",
    "ward": "Ashok Vihar"
  },
  {
    "text": "Ashok Vihar traffic thoda better hua hai situation abhi bhi concerning hai",
    "source": "news",
    "location": "Delhi",
    "ward": "Ashok Vihar"
  },
  {
    "text": "Ashok Vihar traffic thoda better hua hai logon ko dikkat ho rahi hai",
    "source": "news",
    "location": "Delhi",
    "ward": "Ashok Vihar"
  },
  {
    "text": "Ashok Vihar traffic thoda better hua hai situation abhi bhi concerning hai",
    "source": "news",
    "location": "Delhi",
    "ward": "Ashok Vihar"
  },
  {
    "text": "Ashok Vihar traffic thoda better hua hai issue abhi tak resolve nahi hua",
    "source": "news",
    "location": "Delhi",
    "ward": "Ashok Vihar"
  },
  {
    "text": "Paschim Vihar mein pollution moderate hai",
    "source": "twitter",
    "location": "Delhi",
    "ward": "Paschim Vihar"
  },
  {
    "text": "Paschim Vihar mein pollution moderate hai kaafi improvement ki zarurat hai",
    "source": "twitter",
    "location": "Delhi",
    "ward": "Paschim Vihar"
  },
  {
    "text": "Paschim Vihar mein pollution moderate hai issue abhi tak resolve nahi hua",
    "source": "twitter",
    "location": "Delhi",
    "ward": "Paschim Vihar"
  },
  {
    "text": "Paschim Vihar mein pollution moderate hai kaafi improvement ki zarurat hai",
    "source": "twitter",
    "location": "Delhi",
    "ward": "Paschim Vihar"
  },
  {
    "text": "Paschim Vihar mein pollution moderate hai kaafi improvement ki zarurat hai",
    "source": "twitter",
    "location": "Delhi",
    "ward": "Paschim Vihar"
  },
  {
    "text": "Seelampur mein bijli cuts kam ho gaye hain",
    "source": "news",
    "location": "Delhi",
    "ward": "Seelampur"
  },
  {
    "text": "Seelampur mein bijli cuts kam ho gaye hain situation abhi bhi concerning hai",
    "source": "news",
    "location": "Delhi",
    "ward": "Seelampur"
  },
  {
    "text": "Seelampur mein bijli cuts kam ho gaye hain authorities ko action lena chahiye",
    "source": "news",
    "location": "Delhi",
    "ward": "Seelampur"
  },
  {
    "text": "Seelampur mein bijli cuts kam ho gaye hain situation abhi bhi concerning hai",
    "source": "news",
    "location": "Delhi",
    "ward": "Seelampur"
  },
  {
    "text": "Seelampur mein bijli cuts kam ho gaye hain kaafi improvement ki zarurat hai",
    "source": "news",
    "location": "Delhi",
    "ward": "Seelampur"
  },
  {
    "text": "Kashmere Gate roads congested hain peak hours mein",
    "source": "twitter",
    "location": "Delhi",
    "ward": "Kashmere Gate"
  },
  {
    "text": "Kashmere Gate roads congested hain peak hours mein logon ko dikkat ho rahi hai",
    "source": "twitter",
    "location": "Delhi",
    "ward": "Kashmere Gate"
  },
  {
    "text": "Kashmere Gate roads congested hain peak hours mein issue abhi tak resolve nahi hua",
    "source": "twitter",
    "location": "Delhi",
    "ward": "Kashmere Gate"
  },
  {
    "text": "Kashmere Gate roads congested hain peak hours mein logon ko dikkat ho rahi hai",
    "source": "twitter",
    "location": "Delhi",
    "ward": "Kashmere Gate"
  },
  {
    "text": "Kashmere Gate roads congested hain peak hours mein issue abhi tak resolve nahi hua",
    "source": "twitter",
    "location": "Delhi",
    "ward": "Kashmere Gate"
  },
  {
    "text": "Greater Kailash mein water supply theek chal rahi hai",
    "source": "news",
    "location": "Delhi",
    "ward": "Greater Kailash"
  },
  {
    "text": "Greater Kailash mein water supply theek chal rahi hai kaafi improvement ki zarurat hai",
    "source": "news",
    "location": "Delhi",
    "ward": "Greater Kailash"
  },
  {
    "text": "Greater Kailash mein water supply theek chal rahi hai situation abhi bhi concerning hai",
    "source": "news",
    "location": "Delhi",
    "ward": "Greater Kailash"
  },
  {
    "text": "Greater Kailash mein water supply theek chal rahi hai kaafi improvement ki zarurat hai",
    "source": "news",
    "location": "Delhi",
    "ward": "Greater Kailash"
  },
  {
    "text": "Greater Kailash mein water supply theek chal rahi hai logon ko dikkat ho rahi hai",
    "source": "news",
    "location": "Delhi",
    "ward": "Greater Kailash"
  }
]